{
  "meta": {
    "analysis_date": "2026-06-10 10:58:47.418312",
    "data_period_start": "2025-03-01",
    "data_period_end": "2026-06-08",
    "target_week": "2026-W23",
    "target_date_start": "2026-06-01",
    "target_date_end": "2026-06-07",
    "store_name": "shiki-002"
  },
  "sales_analysis": {
    "target_week": {
      "売上": 1322085.0,
      "客数": 59,
      "組数": 77,
      "客単価": 22408.22033898305
    },
    "comparisons": {
      "previous_week": {
        "week": "2026-W22",
        "data": {
          "売上": 1489515.0,
          "客数": 74,
          "客単価": 20128.58108108108
        }
      },
      "previous_month": {
        "week": "2026-W21",
        "data": {
          "売上": 1412879.75,
          "客数": 82,
          "客単価": 17421.02094284522
        }
      },
      "previous_year": {
        "week": "2025-W23",
        "data": {
          "売上": 1325120.0,
          "客数": 101,
          "客単価": 13120.0
        }
      }
    }
  },
  "category_analysis": {
    "target_week": [
      {
        "year_week": "2026-W23",
        "category1": "テイクアウト",
        "subtotal": 602480.0,
        "quantity": 129,
        "構成比": 46.13275955802966
      },
      {
        "year_week": "2026-W23",
        "category1": "フード",
        "subtotal": 294800.0,
        "quantity": 156,
        "構成比": 22.573259722658253
      },
      {
        "year_week": "2026-W23",
        "category1": "デリバリー",
        "subtotal": 243000.0,
        "quantity": 500,
        "構成比": 18.606859269355343
      },
      {
        "year_week": "2026-W23",
        "category1": "ドリンク",
        "subtotal": 82350.0,
        "quantity": 100,
        "構成比": 6.305657863503756
      },
      {
        "year_week": "2026-W23",
        "category1": "コース",
        "subtotal": 63400.0,
        "quantity": 13,
        "構成比": 4.854629126243329
      },
      {
        "year_week": "2026-W23",
        "category1": "ランチ",
        "subtotal": 14600.0,
        "quantity": 4,
        "構成比": 1.1179429849077696
      },
      {
        "year_week": "2026-W23",
        "category1": "ウーバーイーツ",
        "subtotal": 5340.0,
        "quantity": 34,
        "構成比": 0.40889147530188286
      }
    ],
    "previous_week": {
      "year_week": {
        "ウーバーイーツ": "2026-W22",
        "コース": "2026-W22",
        "テイクアウト": "2026-W22",
        "ドリンク": "2026-W22",
        "フード": "2026-W22",
        "ランチ": "2026-W22"
      },
      "subtotal": {
        "ウーバーイーツ": 13460.0,
        "コース": 156960.0,
        "テイクアウト": 730400.0,
        "ドリンク": 123950.0,
        "フード": 414950.0,
        "ランチ": 14900.0
      },
      "quantity": {
        "ウーバーイーツ": 36,
        "コース": 18,
        "テイクアウト": 163,
        "ドリンク": 147,
        "フード": 207,
        "ランチ": 5
      },
      "構成比": {
        "ウーバーイーツ": 0.9253275769616808,
        "コース": 10.790446989591782,
        "テイクアウト": 50.212426613136074,
        "ドリンク": 8.521125792303144,
        "フード": 28.526350524535616,
        "ランチ": 1.024322503471697
      }
    },
    "previous_month": {
      "year_week": {
        "お土産": "2026-W21",
        "ウーバーイーツ": "2026-W21",
        "コース": "2026-W21",
        "テイクアウト": "2026-W21",
        "ドリンク": "2026-W21",
        "フード": "2026-W21",
        "ランチ": "2026-W21"
      },
      "subtotal": {
        "お土産": 300.0,
        "ウーバーイーツ": 4110.0,
        "コース": 129040.0,
        "テイクアウト": 797470.0,
        "ドリンク": 111250.0,
        "フード": 462960.0,
        "ランチ": 105600.0
      },
      "quantity": {
        "お土産": 1,
        "ウーバーイーツ": 27,
        "コース": 16,
        "テイクアウト": 186,
        "ドリンク": 125,
        "フード": 240,
        "ランチ": 17
      },
      "構成比": {
        "お土産": 0.0186250954536142,
        "ウーバーイーツ": 0.2551638077145145,
        "コース": 8.011274391114588,
        "テイクアウト": 49.50984957131239,
        "ドリンク": 6.906806230715266,
        "フード": 28.742247304017432,
        "ランチ": 6.556033599672198
      }
    }
  },
  "product_analysis": {
    "target_week": [
      {
        "year_week": "2026-W23",
        "menu_name": "DX弁当",
        "subtotal": 215000.0,
        "quantity": 430,
        "構成比": 16.462859024326747
      },
      {
        "year_week": "2026-W23",
        "menu_name": "Uberうな重竹",
        "subtotal": 140400.0,
        "quantity": 18,
        "構成比": 10.750629800071977
      },
      {
        "year_week": "2026-W23",
        "menu_name": "Uberうな重松",
        "subtotal": 131600.0,
        "quantity": 14,
        "構成比": 10.076801151634417
      },
      {
        "year_week": "2026-W23",
        "menu_name": "Uberうな重梅",
        "subtotal": 125400.0,
        "quantity": 22,
        "構成比": 9.602058240235227
      },
      {
        "year_week": "2026-W23",
        "menu_name": "ランチうな重",
        "subtotal": 55000.0,
        "quantity": 10,
        "構成比": 4.211429052734749
      },
      {
        "year_week": "2026-W23",
        "menu_name": "ランチ松セット1ドリンク",
        "subtotal": 40600.0,
        "quantity": 7,
        "構成比": 3.108800355291469
      },
      {
        "year_week": "2026-W23",
        "menu_name": "Uberうな重松 肝吸いなし",
        "subtotal": 36400.0,
        "quantity": 4,
        "構成比": 2.787200318537179
      },
      {
        "year_week": "2026-W23",
        "menu_name": "うな重梅",
        "subtotal": 33600.0,
        "quantity": 8,
        "構成比": 2.572800294034319
      },
      {
        "year_week": "2026-W23",
        "menu_name": "うな重竹",
        "subtotal": 29000.0,
        "quantity": 5,
        "構成比": 2.220571682351049
      },
      {
        "year_week": "2026-W23",
        "menu_name": "HC弁当",
        "subtotal": 28000.0,
        "quantity": 70,
        "構成比": 2.1440002450285998
      },
      {
        "year_week": "2026-W23",
        "menu_name": "ランチ梅セット1ドリンク",
        "subtotal": 22800.0,
        "quantity": 6,
        "構成比": 1.7458287709518596
      },
      {
        "year_week": "2026-W23",
        "menu_name": "TOうな重梅",
        "subtotal": 21000.0,
        "quantity": 5,
        "構成比": 1.6080001837714495
      },
      {
        "year_week": "2026-W23",
        "menu_name": "うなぎ蒲焼",
        "subtotal": 18000.0,
        "quantity": 3,
        "構成比": 1.3782858718040996
      },
      {
        "year_week": "2026-W23",
        "menu_name": "うなぎ白焼き",
        "subtotal": 18000.0,
        "quantity": 3,
        "構成比": 1.3782858718040996
      },
      {
        "year_week": "2026-W23",
        "menu_name": "お通し",
        "subtotal": 17500.0,
        "quantity": 25,
        "構成比": 1.3400001531428747
      },
      {
        "year_week": "2026-W23",
        "menu_name": "Uber白焼き",
        "subtotal": 17200.0,
        "quantity": 2,
        "構成比": 1.3170287219461396
      },
      {
        "year_week": "2026-W23",
        "menu_name": "Uber蒲焼き",
        "subtotal": 17200.0,
        "quantity": 2,
        "構成比": 1.3170287219461396
      },
      {
        "year_week": "2026-W23",
        "menu_name": "コーヒー焼酎",
        "subtotal": 16800.0,
        "quantity": 21,
        "構成比": 1.2864001470171595
      },
      {
        "year_week": "2026-W23",
        "menu_name": "Uber肝焼き",
        "subtotal": 15750.0,
        "quantity": 21,
        "構成比": 1.2060001378285872
      },
      {
        "year_week": "2026-W23",
        "menu_name": "menuうな重竹",
        "subtotal": 15600.0,
        "quantity": 2,
        "構成比": 1.1945144222302198
      },
      {
        "year_week": "2026-W23",
        "menu_name": "ｻﾞ･ﾌﾟﾚﾐｱﾑ･ﾓﾙﾂ ﾀﾝﾌﾞﾗｰ",
        "subtotal": 14700.0,
        "quantity": 21,
        "構成比": 1.1256001286400146
      },
      {
        "year_week": "2026-W23",
        "menu_name": "ランチコース",
        "subtotal": 14000.0,
        "quantity": 2,
        "構成比": 1.0720001225142999
      },
      {
        "year_week": "2026-W23",
        "menu_name": "ロケットナウうな重松",
        "subtotal": 13800.0,
        "quantity": 2,
        "構成比": 1.0566858350498098
      },
      {
        "year_week": "2026-W23",
        "menu_name": "ｸﾞﾚﾝﾌﾃﾞｨｯｸ12年",
        "subtotal": 13500.0,
        "quantity": 15,
        "構成比": 1.0337144038530748
      },
      {
        "year_week": "2026-W23",
        "menu_name": "う巻",
        "subtotal": 13500.0,
        "quantity": 3,
        "構成比": 1.0337144038530748
      },
      {
        "year_week": "2026-W23",
        "menu_name": "肝焼き",
        "subtotal": 10800.0,
        "quantity": 18,
        "構成比": 0.8269715230824598
      },
      {
        "year_week": "2026-W23",
        "menu_name": "ランチうな重ハーフ",
        "subtotal": 10500.0,
        "quantity": 3,
        "構成比": 0.8040000918857247
      },
      {
        "year_week": "2026-W23",
        "menu_name": "ふぐ刺し",
        "subtotal": 9500.0,
        "quantity": 2,
        "構成比": 0.7274286545632748
      },
      {
        "year_week": "2026-W23",
        "menu_name": "Uberとろろサラダ",
        "subtotal": 8400.0,
        "quantity": 4,
        "構成比": 0.6432000735085798
      },
      {
        "year_week": "2026-W23",
        "menu_name": "TOうな重松",
        "subtotal": 6900.0,
        "quantity": 1,
        "構成比": 0.5283429175249049
      },
      {
        "year_week": "2026-W23",
        "menu_name": "うな重松",
        "subtotal": 6900.0,
        "quantity": 1,
        "構成比": 0.5283429175249049
      },
      {
        "year_week": "2026-W23",
        "menu_name": "テラザス",
        "subtotal": 6500.0,
        "quantity": 1,
        "構成比": 0.49771434259592484
      },
      {
        "year_week": "2026-W23",
        "menu_name": "Uberうな重ハーフ肝焼き入り",
        "subtotal": 6300.0,
        "quantity": 1,
        "構成比": 0.48240005513143486
      },
      {
        "year_week": "2026-W23",
        "menu_name": "Uberう巻",
        "subtotal": 6100.0,
        "quantity": 1,
        "構成比": 0.4670857676669448
      },
      {
        "year_week": "2026-W23",
        "menu_name": "TOうなぎ白焼き",
        "subtotal": 6000.0,
        "quantity": 1,
        "構成比": 0.4594286239346999
      },
      {
        "year_week": "2026-W23",
        "menu_name": "旬菜3点盛り",
        "subtotal": 6000.0,
        "quantity": 6,
        "構成比": 0.4594286239346999
      },
      {
        "year_week": "2026-W23",
        "menu_name": "TOうな重竹",
        "subtotal": 5800.0,
        "quantity": 1,
        "構成比": 0.4441143364702099
      },
      {
        "year_week": "2026-W23",
        "menu_name": "ロケットナウうな重竹",
        "subtotal": 5800.0,
        "quantity": 1,
        "構成比": 0.4441143364702099
      },
      {
        "year_week": "2026-W23",
        "menu_name": "黒毛和牛うな重",
        "subtotal": 4800.0,
        "quantity": 1,
        "構成比": 0.3675428991477599
      },
      {
        "year_week": "2026-W23",
        "menu_name": "Uber鰻のタレ",
        "subtotal": 4800.0,
        "quantity": 16,
        "構成比": 0.3675428991477599
      },
      {
        "year_week": "2026-W23",
        "menu_name": "蟹味噌クリームコロッケ",
        "subtotal": 4500.0,
        "quantity": 4,
        "構成比": 0.3445714679510249
      },
      {
        "year_week": "2026-W23",
        "menu_name": "ﾒｰｶｰｽﾞﾏｰｸ",
        "subtotal": 4500.0,
        "quantity": 5,
        "構成比": 0.3445714679510249
      },
      {
        "year_week": "2026-W23",
        "menu_name": "TOう巻",
        "subtotal": 4500.0,
        "quantity": 1,
        "構成比": 0.3445714679510249
      },
      {
        "year_week": "2026-W23",
        "menu_name": "Uberおしんこ盛り",
        "subtotal": 4500.0,
        "quantity": 5,
        "構成比": 0.3445714679510249
      },
      {
        "year_week": "2026-W23",
        "menu_name": "ロケットナウうな重梅",
        "subtotal": 4200.0,
        "quantity": 1,
        "構成比": 0.3216000367542899
      },
      {
        "year_week": "2026-W23",
        "menu_name": "オールフリー",
        "subtotal": 4200.0,
        "quantity": 7,
        "構成比": 0.3216000367542899
      },
      {
        "year_week": "2026-W23",
        "menu_name": "太刀魚の春巻き",
        "subtotal": 4000.0,
        "quantity": 4,
        "構成比": 0.30628574928979996
      },
      {
        "year_week": "2026-W23",
        "menu_name": "馬刺し盛り合わせ",
        "subtotal": 3600.0,
        "quantity": 1,
        "構成比": 0.27565717436081993
      },
      {
        "year_week": "2026-W23",
        "menu_name": "あじ",
        "subtotal": 3600.0,
        "quantity": 3,
        "構成比": 0.27565717436081993
      },
      {
        "year_week": "2026-W23",
        "menu_name": "サバの一夜干し定食",
        "subtotal": 3600.0,
        "quantity": 3,
        "構成比": 0.27565717436081993
      },
      {
        "year_week": "2026-W23",
        "menu_name": "ふぐぶつ刺",
        "subtotal": 3500.0,
        "quantity": 1,
        "構成比": 0.26800003062857497
      },
      {
        "year_week": "2026-W23",
        "menu_name": "大和芋のサラダ ﾊｰﾌ",
        "subtotal": 3000.0,
        "quantity": 3,
        "構成比": 0.22971431196734995
      },
      {
        "year_week": "2026-W23",
        "menu_name": "大盛り",
        "subtotal": 3000.0,
        "quantity": 15,
        "構成比": 0.22971431196734995
      },
      {
        "year_week": "2026-W23",
        "menu_name": "チョレギサラダ",
        "subtotal": 3000.0,
        "quantity": 3,
        "構成比": 0.22971431196734995
      },
      {
        "year_week": "2026-W23",
        "menu_name": "うまから揚げ",
        "subtotal": 3000.0,
        "quantity": 3,
        "構成比": 0.22971431196734995
      },
      {
        "year_week": "2026-W23",
        "menu_name": "牡蠣フライ2個",
        "subtotal": 3000.0,
        "quantity": 3,
        "構成比": 0.22971431196734995
      },
      {
        "year_week": "2026-W23",
        "menu_name": "内臓美人ハイ",
        "subtotal": 3000.0,
        "quantity": 3,
        "構成比": 0.22971431196734995
      },
      {
        "year_week": "2026-W23",
        "menu_name": "ウーロン茶",
        "subtotal": 2900.0,
        "quantity": 7,
        "構成比": 0.22205716823510496
      },
      {
        "year_week": "2026-W23",
        "menu_name": "ヒレ串",
        "subtotal": 2800.0,
        "quantity": 7,
        "構成比": 0.21440002450285994
      },
      {
        "year_week": "2026-W23",
        "menu_name": "馬刺 赤身",
        "subtotal": 2800.0,
        "quantity": 2,
        "構成比": 0.21440002450285994
      },
      {
        "year_week": "2026-W23",
        "menu_name": "吉四六 グラス",
        "subtotal": 2550.0,
        "quantity": 3,
        "構成比": 0.19525716517224745
      },
      {
        "year_week": "2026-W23",
        "menu_name": "しき焼酎(芋)",
        "subtotal": 2400.0,
        "quantity": 3,
        "構成比": 0.18377144957387995
      },
      {
        "year_week": "2026-W23",
        "menu_name": "播州一献",
        "subtotal": 2400.0,
        "quantity": 2,
        "構成比": 0.18377144957387995
      },
      {
        "year_week": "2026-W23",
        "menu_name": "おしんこ盛",
        "subtotal": 2100.0,
        "quantity": 3,
        "構成比": 0.16080001837714494
      },
      {
        "year_week": "2026-W23",
        "menu_name": "Uber豆腐サラダ",
        "subtotal": 1900.0,
        "quantity": 1,
        "構成比": 0.14548573091265496
      },
      {
        "year_week": "2026-W23",
        "menu_name": "カキフライ定食",
        "subtotal": 1900.0,
        "quantity": 1,
        "構成比": 0.14548573091265496
      },
      {
        "year_week": "2026-W23",
        "menu_name": "Uberかきフライ",
        "subtotal": 1900.0,
        "quantity": 1,
        "構成比": 0.14548573091265496
      },
      {
        "year_week": "2026-W23",
        "menu_name": "Uberトマト玉ねぎ",
        "subtotal": 1700.0,
        "quantity": 1,
        "構成比": 0.13017144344816498
      },
      {
        "year_week": "2026-W23",
        "menu_name": "ほうれん草胡麻和え",
        "subtotal": 1600.0,
        "quantity": 2,
        "構成比": 0.12251429971591997
      },
      {
        "year_week": "2026-W23",
        "menu_name": "ジンジャーエール",
        "subtotal": 1500.0,
        "quantity": 3,
        "構成比": 0.11485715598367498
      },
      {
        "year_week": "2026-W23",
        "menu_name": "夏野菜のお浸し",
        "subtotal": 1400.0,
        "quantity": 2,
        "構成比": 0.10720001225142997
      },
      {
        "year_week": "2026-W23",
        "menu_name": "うなぎヒレ唐揚げ",
        "subtotal": 1400.0,
        "quantity": 2,
        "構成比": 0.10720001225142997
      },
      {
        "year_week": "2026-W23",
        "menu_name": "亀泉",
        "subtotal": 1300.0,
        "quantity": 1,
        "構成比": 0.09954286851918497
      },
      {
        "year_week": "2026-W23",
        "menu_name": "メヒカリのから揚げ",
        "subtotal": 1200.0,
        "quantity": 1,
        "構成比": 0.09188572478693997
      },
      {
        "year_week": "2026-W23",
        "menu_name": "肝わさ",
        "subtotal": 1200.0,
        "quantity": 1,
        "構成比": 0.09188572478693997
      },
      {
        "year_week": "2026-W23",
        "menu_name": "マグロ山かけ",
        "subtotal": 1100.0,
        "quantity": 1,
        "構成比": 0.08422858105469498
      },
      {
        "year_week": "2026-W23",
        "menu_name": "TOガツ刺し",
        "subtotal": 1100.0,
        "quantity": 1,
        "構成比": 0.08422858105469498
      },
      {
        "year_week": "2026-W23",
        "menu_name": "大和芋の磯辺揚",
        "subtotal": 1000.0,
        "quantity": 1,
        "構成比": 0.07657143732244999
      },
      {
        "year_week": "2026-W23",
        "menu_name": "コーラ",
        "subtotal": 1000.0,
        "quantity": 2,
        "構成比": 0.07657143732244999
      },
      {
        "year_week": "2026-W23",
        "menu_name": "ガツ刺し",
        "subtotal": 1000.0,
        "quantity": 1,
        "構成比": 0.07657143732244999
      },
      {
        "year_week": "2026-W23",
        "menu_name": "たこの唐揚げ",
        "subtotal": 1000.0,
        "quantity": 1,
        "構成比": 0.07657143732244999
      },
      {
        "year_week": "2026-W23",
        "menu_name": "マグロ納豆",
        "subtotal": 1000.0,
        "quantity": 1,
        "構成比": 0.07657143732244999
      },
      {
        "year_week": "2026-W23",
        "menu_name": "六ジン",
        "subtotal": 1000.0,
        "quantity": 1,
        "構成比": 0.07657143732244999
      },
      {
        "year_week": "2026-W23",
        "menu_name": "ライス",
        "subtotal": 900.0,
        "quantity": 3,
        "構成比": 0.06891429359020498
      },
      {
        "year_week": "2026-W23",
        "menu_name": "肝吸",
        "subtotal": 900.0,
        "quantity": 3,
        "構成比": 0.06891429359020498
      },
      {
        "year_week": "2026-W23",
        "menu_name": "ハートランド",
        "subtotal": 900.0,
        "quantity": 1,
        "構成比": 0.06891429359020498
      },
      {
        "year_week": "2026-W23",
        "menu_name": "浦霞本醸酒",
        "subtotal": 900.0,
        "quantity": 1,
        "構成比": 0.06891429359020498
      },
      {
        "year_week": "2026-W23",
        "menu_name": "さつま揚げ",
        "subtotal": 900.0,
        "quantity": 1,
        "構成比": 0.06891429359020498
      },
      {
        "year_week": "2026-W23",
        "menu_name": "しき焼酎(麦)",
        "subtotal": 800.0,
        "quantity": 1,
        "構成比": 0.061257149857959985
      },
      {
        "year_week": "2026-W23",
        "menu_name": "生レモンサワー",
        "subtotal": 800.0,
        "quantity": 1,
        "構成比": 0.061257149857959985
      },
      {
        "year_week": "2026-W23",
        "menu_name": "内臓美人茶",
        "subtotal": 700.0,
        "quantity": 1,
        "構成比": 0.053600006125714986
      },
      {
        "year_week": "2026-W23",
        "menu_name": "肝吸い変更",
        "subtotal": 600.0,
        "quantity": 2,
        "構成比": 0.04594286239346999
      },
      {
        "year_week": "2026-W23",
        "menu_name": "ランチビール",
        "subtotal": 600.0,
        "quantity": 1,
        "構成比": 0.04594286239346999
      },
      {
        "year_week": "2026-W23",
        "menu_name": "Uber山椒小袋",
        "subtotal": 540.0,
        "quantity": 18,
        "構成比": 0.04134857615412299
      },
      {
        "year_week": "2026-W23",
        "menu_name": "緑茶",
        "subtotal": 500.0,
        "quantity": 1,
        "構成比": 0.038285718661224995
      },
      {
        "year_week": "2026-W23",
        "menu_name": "カキフライ1個",
        "subtotal": 500.0,
        "quantity": 1,
        "構成比": 0.038285718661224995
      },
      {
        "year_week": "2026-W23",
        "menu_name": "梅干し",
        "subtotal": 400.0,
        "quantity": 2,
        "構成比": 0.030628574928979992
      },
      {
        "year_week": "2026-W23",
        "menu_name": "ランチサラダ",
        "subtotal": 350.0,
        "quantity": 1,
        "構成比": 0.026800003062857493
      },
      {
        "year_week": "2026-W23",
        "menu_name": "とろろ",
        "subtotal": 350.0,
        "quantity": 1,
        "構成比": 0.026800003062857493
      },
      {
        "year_week": "2026-W23",
        "menu_name": "ロケットナウ山椒小袋",
        "subtotal": 30.0,
        "quantity": 1,
        "構成比": 0.002297143119673499
      }
    ],
    "previous_week": {
      "year_week": {
        "TOうな重松": "2026-W22",
        "TOうな重梅": "2026-W22",
        "TOうな重竹": "2026-W22",
        "TOおしんこ盛": "2026-W22",
        "TOガツ刺し": "2026-W22",
        "TO肝焼き": "2026-W22",
        "Uberうな重ハーフ肝焼き入り": "2026-W22",
        "Uberうな重松": "2026-W22",
        "Uberうな重松 肝吸いなし": "2026-W22",
        "Uberうな重梅": "2026-W22",
        "Uberうな重梅 肝吸いなし": "2026-W22",
        "Uberうな重竹": "2026-W22",
        "Uberう巻": "2026-W22",
        "Uberおしんこ盛り": "2026-W22",
        "Uberとろろサラダ": "2026-W22",
        "Uberほうれん草胡麻和え": "2026-W22",
        "Uberチョレギサラダ": "2026-W22",
        "Uberヒレ唐揚げ": "2026-W22",
        "Uber冷やしトマト": "2026-W22",
        "Uber大和芋いそべ揚げ": "2026-W22",
        "Uber山椒小袋": "2026-W22",
        "Uber白焼き": "2026-W22",
        "Uber肝焼き": "2026-W22",
        "Uber蒲焼き": "2026-W22",
        "Uber豆腐サラダ": "2026-W22",
        "Uber骨せんべい": "2026-W22",
        "Uber鰻のタレ": "2026-W22",
        "Uber鶏唐揚げ": "2026-W22",
        "menuうな重梅": "2026-W22",
        "menu大和芋いそべ揚げ": "2026-W22",
        "あじ": "2026-W22",
        "うなぎ白焼き": "2026-W22",
        "うなぎ白焼き(ハーフ)": "2026-W22",
        "うなぎ蒲焼": "2026-W22",
        "うなぎ蒲焼(ハーフ)": "2026-W22",
        "うな重松": "2026-W22",
        "うな重梅": "2026-W22",
        "うな重竹": "2026-W22",
        "うまから揚げ": "2026-W22",
        "う巻": "2026-W22",
        "おしんこ盛": "2026-W22",
        "お通し": "2026-W22",
        "ぎんだら焼": "2026-W22",
        "さつま揚げ": "2026-W22",
        "しき焼酎(芋)": "2026-W22",
        "しき焼酎(麦) ボトル": "2026-W22",
        "しょうが焼き定食": "2026-W22",
        "たこの唐揚げ": "2026-W22",
        "とり天定食４個": "2026-W22",
        "とろろ": "2026-W22",
        "ふき味噌": "2026-W22",
        "ふぐから揚げ": "2026-W22",
        "ふぐぶつ刺": "2026-W22",
        "ほうれん草胡麻和え": "2026-W22",
        "ゆず酒": "2026-W22",
        "ウーロン茶": "2026-W22",
        "エシャレット": "2026-W22",
        "オレンジジュース": "2026-W22",
        "オールフリー": "2026-W22",
        "カキフライ1個": "2026-W22",
        "ガツ刺し": "2026-W22",
        "コーラ": "2026-W22",
        "サッポロ黒ラベル(瓶)": "2026-W22",
        "サバの一夜干し定食": "2026-W22",
        "トマトじゃこ": "2026-W22",
        "トマト玉ねぎ": "2026-W22",
        "ハスのきんぴら": "2026-W22",
        "ヒレ串": "2026-W22",
        "ボトルセット)水": "2026-W22",
        "ボトルセット)氷": "2026-W22",
        "ボトルセット)炭酸": "2026-W22",
        "ライス": "2026-W22",
        "ランチうな重": "2026-W22",
        "ランチコース": "2026-W22",
        "ランチ松セット1ドリンク": "2026-W22",
        "ランチ梅セット1ドリンク": "2026-W22",
        "ロケットナウうな重松": "2026-W22",
        "ロケットナウうな重梅": "2026-W22",
        "ロケットナウうな重竹": "2026-W22",
        "ロケットナウとろろサラダ": "2026-W22",
        "ロケットナウ山椒小袋": "2026-W22",
        "ロケットナウ肝焼き": "2026-W22",
        "三岳 グラス": "2026-W22",
        "三岳 ボトル": "2026-W22",
        "下関ふぐづくしコース": "2026-W22",
        "伊七郎グラス": "2026-W22",
        "六ジン": "2026-W22",
        "内臓美人茶": "2026-W22",
        "冷やしトマト": "2026-W22",
        "夏野菜のお浸し": "2026-W22",
        "大和芋のとろろサラダ": "2026-W22",
        "大和芋の磯辺揚": "2026-W22",
        "大盛り": "2026-W22",
        "太刀魚の春巻き": "2026-W22",
        "平日限定　うな玉＋肝焼": "2026-W22",
        "持ち込みボトル": "2026-W22",
        "播州一献": "2026-W22",
        "旬菜3点盛り": "2026-W22",
        "本マグロ": "2026-W22",
        "浦霞本醸酒": "2026-W22",
        "牡蠣フライ2個": "2026-W22",
        "生レモンサワー": "2026-W22",
        "生卵": "2026-W22",
        "生ｸﾞﾚｰﾌﾟﾌﾙｰﾂｻﾜｰ": "2026-W22",
        "緑茶": "2026-W22",
        "緑茶ハイ": "2026-W22",
        "縞ホッケ焼": "2026-W22",
        "羽根屋": "2026-W22",
        "肝吸い変更": "2026-W22",
        "肝焼き": "2026-W22",
        "自家製レモンサワー": "2026-W22",
        "蟹味噌クリームコロッケ": "2026-W22",
        "西の関": "2026-W22",
        "誕生日プレート": "2026-W22",
        "貴": "2026-W22",
        "酔鯨": "2026-W22",
        "銀盤純米大吟醸": "2026-W22",
        "馬刺 赤身": "2026-W22",
        "馬刺し盛り合わせ": "2026-W22",
        "骨せんべい": "2026-W22",
        "鰻ざく": "2026-W22",
        "麻布しきコース": "2026-W22",
        "黒毛和牛うな重": "2026-W22",
        "ｱｻﾋｽｰﾊﾟｰﾄﾞﾗｲ(瓶)": "2026-W22",
        "ｸﾞﾚﾝﾌﾃﾞｨｯｸ12年": "2026-W22",
        "ｻﾞ･ﾌﾟﾚﾐｱﾑ･ﾓﾙﾂ 小生": "2026-W22",
        "ｻﾞ･ﾌﾟﾚﾐｱﾑ･ﾓﾙﾂ ﾀﾝﾌﾞﾗｰ": "2026-W22"
      },
      "subtotal": {
        "TOうな重松": 69000.0,
        "TOうな重梅": 12600.0,
        "TOうな重竹": 11600.0,
        "TOおしんこ盛": 770.0,
        "TOガツ刺し": 1100.0,
        "TO肝焼き": 600.0,
        "Uberうな重ハーフ肝焼き入り": 37800.0,
        "Uberうな重松": 141000.0,
        "Uberうな重松 肝吸いなし": 27300.0,
        "Uberうな重梅": 148200.0,
        "Uberうな重梅 肝吸いなし": 5400.0,
        "Uberうな重竹": 140400.0,
        "Uberう巻": 6100.0,
        "Uberおしんこ盛り": 3600.0,
        "Uberとろろサラダ": 23100.0,
        "Uberほうれん草胡麻和え": 4800.0,
        "Uberチョレギサラダ": 5700.0,
        "Uberヒレ唐揚げ": 900.0,
        "Uber冷やしトマト": 2000.0,
        "Uber大和芋いそべ揚げ": 3800.0,
        "Uber山椒小袋": 360.0,
        "Uber白焼き": 8600.0,
        "Uber肝焼き": 8250.0,
        "Uber蒲焼き": 8600.0,
        "Uber豆腐サラダ": 3800.0,
        "Uber骨せんべい": 800.0,
        "Uber鰻のタレ": 5700.0,
        "Uber鶏唐揚げ": 5400.0,
        "menuうな重梅": 5700.0,
        "menu大和芋いそべ揚げ": 1800.0,
        "あじ": 3600.0,
        "うなぎ白焼き": 30000.0,
        "うなぎ白焼き(ハーフ)": 7200.0,
        "うなぎ蒲焼": 18000.0,
        "うなぎ蒲焼(ハーフ)": 3600.0,
        "うな重松": 27600.0,
        "うな重梅": 71400.0,
        "うな重竹": 46400.0,
        "うまから揚げ": 6000.0,
        "う巻": 22500.0,
        "おしんこ盛": 3500.0,
        "お通し": 31500.0,
        "ぎんだら焼": 1800.0,
        "さつま揚げ": 900.0,
        "しき焼酎(芋)": 1600.0,
        "しき焼酎(麦) ボトル": 5500.0,
        "しょうが焼き定食": 1200.0,
        "たこの唐揚げ": 2000.0,
        "とり天定食４個": 1100.0,
        "とろろ": 350.0,
        "ふき味噌": 900.0,
        "ふぐから揚げ": 8000.0,
        "ふぐぶつ刺": 6000.0,
        "ほうれん草胡麻和え": 4000.0,
        "ゆず酒": 800.0,
        "ウーロン茶": 5500.0,
        "エシャレット": 2400.0,
        "オレンジジュース": 500.0,
        "オールフリー": 3600.0,
        "カキフライ1個": 1000.0,
        "ガツ刺し": 2000.0,
        "コーラ": 1500.0,
        "サッポロ黒ラベル(瓶)": 900.0,
        "サバの一夜干し定食": 1200.0,
        "トマトじゃこ": 900.0,
        "トマト玉ねぎ": 1800.0,
        "ハスのきんぴら": 1200.0,
        "ヒレ串": 400.0,
        "ボトルセット)水": 300.0,
        "ボトルセット)氷": 2400.0,
        "ボトルセット)炭酸": 7800.0,
        "ライス": 800.0,
        "ランチうな重": 27500.0,
        "ランチコース": 14000.0,
        "ランチ松セット1ドリンク": 29000.0,
        "ランチ梅セット1ドリンク": 7600.0,
        "ロケットナウうな重松": 6900.0,
        "ロケットナウうな重梅": 12600.0,
        "ロケットナウうな重竹": 29000.0,
        "ロケットナウとろろサラダ": 1540.0,
        "ロケットナウ山椒小袋": 240.0,
        "ロケットナウ肝焼き": 1200.0,
        "三岳 グラス": 2550.0,
        "三岳 ボトル": 6500.0,
        "下関ふぐづくしコース": 44000.0,
        "伊七郎グラス": 900.0,
        "六ジン": 2800.0,
        "内臓美人茶": 700.0,
        "冷やしトマト": 2400.0,
        "夏野菜のお浸し": 2100.0,
        "大和芋のとろろサラダ": 1400.0,
        "大和芋の磯辺揚": 3000.0,
        "大盛り": 3000.0,
        "太刀魚の春巻き": 5000.0,
        "平日限定　うな玉＋肝焼": 6360.0,
        "持ち込みボトル": 6000.0,
        "播州一献": 4800.0,
        "旬菜3点盛り": 4000.0,
        "本マグロ": 8800.0,
        "浦霞本醸酒": 2700.0,
        "牡蠣フライ2個": 3000.0,
        "生レモンサワー": 3200.0,
        "生卵": 200.0,
        "生ｸﾞﾚｰﾌﾟﾌﾙｰﾂｻﾜｰ": 900.0,
        "緑茶": 500.0,
        "緑茶ハイ": 1400.0,
        "縞ホッケ焼": 2600.0,
        "羽根屋": 3900.0,
        "肝吸い変更": 900.0,
        "肝焼き": 9000.0,
        "自家製レモンサワー": 4500.0,
        "蟹味噌クリームコロッケ": 1000.0,
        "西の関": 5000.0,
        "誕生日プレート": 200.0,
        "貴": 10000.0,
        "酔鯨": 3300.0,
        "銀盤純米大吟醸": 3600.0,
        "馬刺 赤身": 7000.0,
        "馬刺し盛り合わせ": 14400.0,
        "骨せんべい": 1200.0,
        "鰻ざく": 2700.0,
        "麻布しきコース": 70000.0,
        "黒毛和牛うな重": 4800.0,
        "ｱｻﾋｽｰﾊﾟｰﾄﾞﾗｲ(瓶)": 2700.0,
        "ｸﾞﾚﾝﾌﾃﾞｨｯｸ12年": 1800.0,
        "ｻﾞ･ﾌﾟﾚﾐｱﾑ･ﾓﾙﾂ 小生": 2700.0,
        "ｻﾞ･ﾌﾟﾚﾐｱﾑ･ﾓﾙﾂ ﾀﾝﾌﾞﾗｰ": 23100.0
      },
      "quantity": {
        "TOうな重松": 10,
        "TOうな重梅": 3,
        "TOうな重竹": 2,
        "TOおしんこ盛": 1,
        "TOガツ刺し": 1,
        "TO肝焼き": 1,
        "Uberうな重ハーフ肝焼き入り": 6,
        "Uberうな重松": 15,
        "Uberうな重松 肝吸いなし": 3,
        "Uberうな重梅": 26,
        "Uberうな重梅 肝吸いなし": 1,
        "Uberうな重竹": 18,
        "Uberう巻": 1,
        "Uberおしんこ盛り": 4,
        "Uberとろろサラダ": 11,
        "Uberほうれん草胡麻和え": 4,
        "Uberチョレギサラダ": 3,
        "Uberヒレ唐揚げ": 1,
        "Uber冷やしトマト": 2,
        "Uber大和芋いそべ揚げ": 2,
        "Uber山椒小袋": 12,
        "Uber白焼き": 1,
        "Uber肝焼き": 11,
        "Uber蒲焼き": 1,
        "Uber豆腐サラダ": 2,
        "Uber骨せんべい": 1,
        "Uber鰻のタレ": 19,
        "Uber鶏唐揚げ": 3,
        "menuうな重梅": 1,
        "menu大和芋いそべ揚げ": 1,
        "あじ": 3,
        "うなぎ白焼き": 5,
        "うなぎ白焼き(ハーフ)": 2,
        "うなぎ蒲焼": 3,
        "うなぎ蒲焼(ハーフ)": 1,
        "うな重松": 4,
        "うな重梅": 17,
        "うな重竹": 8,
        "うまから揚げ": 6,
        "う巻": 5,
        "おしんこ盛": 5,
        "お通し": 45,
        "ぎんだら焼": 1,
        "さつま揚げ": 1,
        "しき焼酎(芋)": 2,
        "しき焼酎(麦) ボトル": 1,
        "しょうが焼き定食": 1,
        "たこの唐揚げ": 2,
        "とり天定食４個": 1,
        "とろろ": 1,
        "ふき味噌": 1,
        "ふぐから揚げ": 2,
        "ふぐぶつ刺": 1,
        "ほうれん草胡麻和え": 5,
        "ゆず酒": 1,
        "ウーロン茶": 11,
        "エシャレット": 3,
        "オレンジジュース": 1,
        "オールフリー": 6,
        "カキフライ1個": 2,
        "ガツ刺し": 2,
        "コーラ": 3,
        "サッポロ黒ラベル(瓶)": 1,
        "サバの一夜干し定食": 1,
        "トマトじゃこ": 1,
        "トマト玉ねぎ": 2,
        "ハスのきんぴら": 2,
        "ヒレ串": 1,
        "ボトルセット)水": 1,
        "ボトルセット)氷": 8,
        "ボトルセット)炭酸": 13,
        "ライス": 4,
        "ランチうな重": 5,
        "ランチコース": 2,
        "ランチ松セット1ドリンク": 5,
        "ランチ梅セット1ドリンク": 2,
        "ロケットナウうな重松": 1,
        "ロケットナウうな重梅": 3,
        "ロケットナウうな重竹": 5,
        "ロケットナウとろろサラダ": 1,
        "ロケットナウ山椒小袋": 8,
        "ロケットナウ肝焼き": 2,
        "三岳 グラス": 3,
        "三岳 ボトル": 1,
        "下関ふぐづくしコース": 2,
        "伊七郎グラス": 1,
        "六ジン": 3,
        "内臓美人茶": 1,
        "冷やしトマト": 3,
        "夏野菜のお浸し": 3,
        "大和芋のとろろサラダ": 1,
        "大和芋の磯辺揚": 3,
        "大盛り": 15,
        "太刀魚の春巻き": 5,
        "平日限定　うな玉＋肝焼": 2,
        "持ち込みボトル": 2,
        "播州一献": 4,
        "旬菜3点盛り": 4,
        "本マグロ": 4,
        "浦霞本醸酒": 3,
        "牡蠣フライ2個": 3,
        "生レモンサワー": 4,
        "生卵": 1,
        "生ｸﾞﾚｰﾌﾟﾌﾙｰﾂｻﾜｰ": 1,
        "緑茶": 1,
        "緑茶ハイ": 2,
        "縞ホッケ焼": 2,
        "羽根屋": 3,
        "肝吸い変更": 3,
        "肝焼き": 15,
        "自家製レモンサワー": 5,
        "蟹味噌クリームコロッケ": 1,
        "西の関": 5,
        "誕生日プレート": 1,
        "貴": 10,
        "酔鯨": 3,
        "銀盤純米大吟醸": 3,
        "馬刺 赤身": 5,
        "馬刺し盛り合わせ": 4,
        "骨せんべい": 2,
        "鰻ざく": 3,
        "麻布しきコース": 7,
        "黒毛和牛うな重": 1,
        "ｱｻﾋｽｰﾊﾟｰﾄﾞﾗｲ(瓶)": 3,
        "ｸﾞﾚﾝﾌﾃﾞｨｯｸ12年": 2,
        "ｻﾞ･ﾌﾟﾚﾐｱﾑ･ﾓﾙﾂ 小生": 6,
        "ｻﾞ･ﾌﾟﾚﾐｱﾑ･ﾓﾙﾂ ﾀﾝﾌﾞﾗｰ": 33
      },
      "構成比": {
        "TOうな重松": 4.743506895271618,
        "TOうな重梅": 0.8662056069626431,
        "TOうな重竹": 0.7974591302195763,
        "TOおしんこ盛": 0.05293478709216153,
        "TOガツ刺し": 0.07562112441737362,
        "TO肝焼き": 0.04124788604584015,
        "Uberうな重ハーフ肝焼き入り": 2.5986168208879294,
        "Uberうな重松": 9.693253220772435,
        "Uberうな重松 肝吸いなし": 1.8767788150857267,
        "Uberうな重梅": 10.188227853322518,
        "Uberうな重梅 肝吸いなし": 0.37123097441256137,
        "Uberうな重竹": 9.652005334726594,
        "Uberう巻": 0.4193535081327082,
        "Uberおしんこ盛り": 0.2474873162750409,
        "Uberとろろサラダ": 1.5880436127648458,
        "Uberほうれん草胡麻和え": 0.3299830883667212,
        "Uberチョレギサラダ": 0.3918549174354814,
        "Uberヒレ唐揚げ": 0.06187182906876022,
        "Uber冷やしトマト": 0.13749295348613383,
        "Uber大和芋いそべ揚げ": 0.2612366116236543,
        "Uber山椒小袋": 0.02474873162750409,
        "Uber白焼き": 0.5912196999903755,
        "Uber肝焼き": 0.5671584331303021,
        "Uber蒲焼き": 0.5912196999903755,
        "Uber豆腐サラダ": 0.2612366116236543,
        "Uber骨せんべい": 0.05499718139445354,
        "Uber鰻のタレ": 0.3918549174354814,
        "Uber鶏唐揚げ": 0.37123097441256137,
        "menuうな重梅": 0.3918549174354814,
        "menu大和芋いそべ揚げ": 0.12374365813752045,
        "あじ": 0.2474873162750409,
        "うなぎ白焼き": 2.0623943022920073,
        "うなぎ白焼き(ハーフ)": 0.4949746325500818,
        "うなぎ蒲焼": 1.2374365813752044,
        "うなぎ蒲焼(ハーフ)": 0.2474873162750409,
        "うな重松": 1.8974027581086468,
        "うな重梅": 4.908498439454978,
        "うな重竹": 3.189836520878305,
        "うまから揚げ": 0.4124788604584015,
        "う巻": 1.5467957267190056,
        "おしんこ盛": 0.24061266860073421,
        "お通し": 2.165514017406608,
        "ぎんだら焼": 0.12374365813752045,
        "さつま揚げ": 0.06187182906876022,
        "しき焼酎(芋)": 0.10999436278890708,
        "しき焼酎(麦) ボトル": 0.37810562208686804,
        "しょうが焼き定食": 0.0824957720916803,
        "たこの唐揚げ": 0.13749295348613383,
        "とり天定食４個": 0.07562112441737362,
        "とろろ": 0.02406126686007342,
        "ふき味噌": 0.06187182906876022,
        "ふぐから揚げ": 0.5499718139445353,
        "ふぐぶつ刺": 0.4124788604584015,
        "ほうれん草胡麻和え": 0.27498590697226766,
        "ゆず酒": 0.05499718139445354,
        "ウーロン茶": 0.37810562208686804,
        "エシャレット": 0.1649915441833606,
        "オレンジジュース": 0.03437323837153346,
        "オールフリー": 0.2474873162750409,
        "カキフライ1個": 0.06874647674306691,
        "ガツ刺し": 0.13749295348613383,
        "コーラ": 0.10311971511460037,
        "サッポロ黒ラベル(瓶)": 0.06187182906876022,
        "サバの一夜干し定食": 0.0824957720916803,
        "トマトじゃこ": 0.06187182906876022,
        "トマト玉ねぎ": 0.12374365813752045,
        "ハスのきんぴら": 0.0824957720916803,
        "ヒレ串": 0.02749859069722677,
        "ボトルセット)水": 0.020623943022920074,
        "ボトルセット)氷": 0.1649915441833606,
        "ボトルセット)炭酸": 0.536222518595922,
        "ライス": 0.05499718139445354,
        "ランチうな重": 1.89052811043434,
        "ランチコース": 0.9624506744029369,
        "ランチ松セット1ドリンク": 1.9936478255489405,
        "ランチ梅セット1ドリンク": 0.5224732232473086,
        "ロケットナウうな重松": 0.4743506895271617,
        "ロケットナウうな重梅": 0.8662056069626431,
        "ロケットナウうな重竹": 1.9936478255489405,
        "ロケットナウとろろサラダ": 0.10586957418432306,
        "ロケットナウ山椒小袋": 0.016499154418336062,
        "ロケットナウ肝焼き": 0.0824957720916803,
        "三岳 グラス": 0.17530351569482064,
        "三岳 ボトル": 0.446852098829935,
        "下関ふぐづくしコース": 3.0248449766949443,
        "伊七郎グラス": 0.06187182906876022,
        "六ジン": 0.19249013488058736,
        "内臓美人茶": 0.04812253372014684,
        "冷やしトマト": 0.1649915441833606,
        "夏野菜のお浸し": 0.14436760116044053,
        "大和芋のとろろサラダ": 0.09624506744029368,
        "大和芋の磯辺揚": 0.20623943022920074,
        "大盛り": 0.20623943022920074,
        "太刀魚の春巻き": 0.34373238371533454,
        "平日限定　うな玉＋肝焼": 0.43722759208590556,
        "持ち込みボトル": 0.4124788604584015,
        "播州一献": 0.3299830883667212,
        "旬菜3点盛り": 0.27498590697226766,
        "本マグロ": 0.604968995338989,
        "浦霞本醸酒": 0.18561548720628068,
        "牡蠣フライ2個": 0.20623943022920074,
        "生レモンサワー": 0.21998872557781415,
        "生卵": 0.013749295348613385,
        "生ｸﾞﾚｰﾌﾟﾌﾙｰﾂｻﾜｰ": 0.06187182906876022,
        "緑茶": 0.03437323837153346,
        "緑茶ハイ": 0.09624506744029368,
        "縞ホッケ焼": 0.178740839531974,
        "羽根屋": 0.268111259297961,
        "肝吸い変更": 0.06187182906876022,
        "肝焼き": 0.6187182906876022,
        "自家製レモンサワー": 0.3093591453438011,
        "蟹味噌クリームコロッケ": 0.06874647674306691,
        "西の関": 0.34373238371533454,
        "誕生日プレート": 0.013749295348613385,
        "貴": 0.6874647674306691,
        "酔鯨": 0.2268633732521208,
        "銀盤純米大吟醸": 0.2474873162750409,
        "馬刺 赤身": 0.48122533720146843,
        "馬刺し盛り合わせ": 0.9899492651001636,
        "骨せんべい": 0.0824957720916803,
        "鰻ざく": 0.18561548720628068,
        "麻布しきコース": 4.812253372014684,
        "黒毛和牛うな重": 0.3299830883667212,
        "ｱｻﾋｽｰﾊﾟｰﾄﾞﾗｲ(瓶)": 0.18561548720628068,
        "ｸﾞﾚﾝﾌﾃﾞｨｯｸ12年": 0.12374365813752045,
        "ｻﾞ･ﾌﾟﾚﾐｱﾑ･ﾓﾙﾂ 小生": 0.18561548720628068,
        "ｻﾞ･ﾌﾟﾚﾐｱﾑ･ﾓﾙﾂ ﾀﾝﾌﾞﾗｰ": 1.5880436127648458
      }
    },
    "previous_month": {
      "year_week": {
        "TOうなぎ白焼き": "2026-W21",
        "TOうなぎ蒲焼": "2026-W21",
        "TOうな重松": "2026-W21",
        "TOうな重梅": "2026-W21",
        "TOうな重竹": "2026-W21",
        "TOう巻": "2026-W21",
        "TOフリー": "2026-W21",
        "Uberうな重ハーフ肝焼き入り": "2026-W21",
        "Uberうな重松": "2026-W21",
        "Uberうな重梅": "2026-W21",
        "Uberうな重梅 肝吸いなし": "2026-W21",
        "Uberうな重竹": "2026-W21",
        "Uberうな重竹 肝吸いなし": "2026-W21",
        "Uberう巻": "2026-W21",
        "Uberおしんこ盛り": "2026-W21",
        "Uberかきフライ": "2026-W21",
        "Uberぎんだら焼": "2026-W21",
        "Uberとろろサラダ": "2026-W21",
        "Uberほうれん草胡麻和え": "2026-W21",
        "Uberガツ刺し": "2026-W21",
        "Uberタコ唐": "2026-W21",
        "Uberヒレ唐揚げ": "2026-W21",
        "Uber大和芋いそべ揚げ": "2026-W21",
        "Uber山椒小袋": "2026-W21",
        "Uber白焼き": "2026-W21",
        "Uber肝焼き": "2026-W21",
        "Uber豆腐サラダ": "2026-W21",
        "Uber鰻のタレ": "2026-W21",
        "Uber鶏唐揚げ": "2026-W21",
        "あじ": "2026-W21",
        "うなぎヒレ唐揚げ": "2026-W21",
        "うなぎ白焼き": "2026-W21",
        "うなぎ白焼き(ハーフ)": "2026-W21",
        "うなぎ蒲焼": "2026-W21",
        "うなとろ丼": "2026-W21",
        "うな玉丼": "2026-W21",
        "うな重松": "2026-W21",
        "うな重梅": "2026-W21",
        "うな重竹": "2026-W21",
        "うまから揚げ": "2026-W21",
        "う巻": "2026-W21",
        "おしんこ盛": "2026-W21",
        "おまかせコース": "2026-W21",
        "お通し": "2026-W21",
        "ぎんだら焼": "2026-W21",
        "さつま揚げ": "2026-W21",
        "しき焼酎(芋)": "2026-W21",
        "しき焼酎(麦)": "2026-W21",
        "しょうが焼き定食": "2026-W21",
        "たこの唐揚げ": "2026-W21",
        "ふぐ刺し": "2026-W21",
        "ほうれん草胡麻和え": "2026-W21",
        "ゆず酒": "2026-W21",
        "ウーロン茶": "2026-W21",
        "エシャレット": "2026-W21",
        "オレンジジュース": "2026-W21",
        "オールフリー": "2026-W21",
        "カキフライ1個": "2026-W21",
        "ガツ刺し": "2026-W21",
        "グレンフィディックボトル": "2026-W21",
        "コーラ": "2026-W21",
        "サバの一夜干し": "2026-W21",
        "ジンジャーエール": "2026-W21",
        "ズワイガニと春菊": "2026-W21",
        "トマトじゃこ": "2026-W21",
        "ハートランド": "2026-W21",
        "フードフリー": "2026-W21",
        "フードフリー税込": "2026-W21",
        "ボトルセット)水": "2026-W21",
        "ボトルセット)氷": "2026-W21",
        "ボトルセット)炭酸": "2026-W21",
        "マグロ山かけ": "2026-W21",
        "マグロ納豆": "2026-W21",
        "メヒカリのから揚げ": "2026-W21",
        "ライス": "2026-W21",
        "ランチうな重": "2026-W21",
        "ランチうな重ハーフ": "2026-W21",
        "ランチコース": "2026-W21",
        "ランチビール": "2026-W21",
        "ランチ松セット1ドリンク": "2026-W21",
        "ロケットナウうな重松": "2026-W21",
        "ロケットナウうな重梅": "2026-W21",
        "ロケットナウうな重竹": "2026-W21",
        "ロケットナウおしんこ盛り": "2026-W21",
        "ロケットナウほうれん草胡麻和え": "2026-W21",
        "ロケットナウタコ唐": "2026-W21",
        "ロケットナウ山椒小袋": "2026-W21",
        "ロケットナウ肝焼き": "2026-W21",
        "ロケットナウ骨せんべい": "2026-W21",
        "ロケットナウ鰻のタレ": "2026-W21",
        "三岳 グラス": "2026-W21",
        "三岳 ボトル": "2026-W21",
        "亀泉": "2026-W21",
        "内臓美人茶": "2026-W21",
        "冷やしトマト": "2026-W21",
        "吉四六 グラス": "2026-W21",
        "吉四六 ボトル": "2026-W21",
        "味噌汁": "2026-W21",
        "大和芋のとろろサラダ": "2026-W21",
        "大和芋のサラダ ﾊｰﾌ": "2026-W21",
        "大和芋の磯辺揚": "2026-W21",
        "大盛り": "2026-W21",
        "太刀魚の春巻き": "2026-W21",
        "旬菜3点盛り": "2026-W21",
        "梅干し": "2026-W21",
        "梅酒": "2026-W21",
        "牡蠣フライ2個": "2026-W21",
        "特選抹茶割": "2026-W21",
        "生レモンサワー": "2026-W21",
        "生ｸﾞﾚｰﾌﾟﾌﾙｰﾂｻﾜｰ": "2026-W21",
        "白州": "2026-W21",
        "緑茶": "2026-W21",
        "縞ホッケ焼": "2026-W21",
        "肝わさ": "2026-W21",
        "肝吸": "2026-W21",
        "肝吸い": "2026-W21",
        "肝吸い変更": "2026-W21",
        "肝焼き": "2026-W21",
        "自家製らっきょう": "2026-W21",
        "蟹味噌クリームコロッケ": "2026-W21",
        "西の関": "2026-W21",
        "豆腐サラダ": "2026-W21",
        "豆腐サラダ ハーフ": "2026-W21",
        "酔鯨": "2026-W21",
        "銀盤純米大吟醸": "2026-W21",
        "馬刺 赤身": "2026-W21",
        "馬刺し盛り合わせ": "2026-W21",
        "骨せんべい": "2026-W21",
        "鰻ぷりん": "2026-W21",
        "麻布しきコース": "2026-W21",
        "麻布しき本店満喫コース": "2026-W21",
        "ｱｻﾋｽｰﾊﾟｰﾄﾞﾗｲ(瓶)": "2026-W21",
        "ｸﾞﾚﾝﾌﾃﾞｨｯｸ12年": "2026-W21",
        "ｻﾞ･ﾌﾟﾚﾐｱﾑ･ﾓﾙﾂ 小生": "2026-W21",
        "ｻﾞ･ﾌﾟﾚﾐｱﾑ･ﾓﾙﾂ ﾀﾝﾌﾞﾗｰ": "2026-W21",
        "ﾒｰｶｰｽﾞﾏｰｸ": "2026-W21"
      },
      "subtotal": {
        "TOうなぎ白焼き": 6000.0,
        "TOうなぎ蒲焼": 6000.0,
        "TOうな重松": 27600.0,
        "TOうな重梅": 4200.0,
        "TOうな重竹": 17400.0,
        "TOう巻": 4500.0,
        "TOフリー": 300.0,
        "Uberうな重ハーフ肝焼き入り": 37800.0,
        "Uberうな重松": 169200.0,
        "Uberうな重梅": 159600.0,
        "Uberうな重梅 肝吸いなし": 10800.0,
        "Uberうな重竹": 156000.0,
        "Uberうな重竹 肝吸いなし": 7500.0,
        "Uberう巻": 12200.0,
        "Uberおしんこ盛り": 1800.0,
        "Uberかきフライ": 3800.0,
        "Uberぎんだら焼": 2900.0,
        "Uberとろろサラダ": 16800.0,
        "Uberほうれん草胡麻和え": 2400.0,
        "Uberガツ刺し": 1900.0,
        "Uberタコ唐": 3600.0,
        "Uberヒレ唐揚げ": 900.0,
        "Uber大和芋いそべ揚げ": 1900.0,
        "Uber山椒小袋": 510.0,
        "Uber白焼き": 43000.0,
        "Uber肝焼き": 13500.0,
        "Uber豆腐サラダ": 3800.0,
        "Uber鰻のタレ": 2700.0,
        "Uber鶏唐揚げ": 7200.0,
        "あじ": 1200.0,
        "うなぎヒレ唐揚げ": 1400.0,
        "うなぎ白焼き": 18000.0,
        "うなぎ白焼き(ハーフ)": 10800.0,
        "うなぎ蒲焼": 6000.0,
        "うなとろ丼": 8640.0,
        "うな玉丼": 11120.0,
        "うな重松": 41400.0,
        "うな重梅": 63000.0,
        "うな重竹": 29000.0,
        "うまから揚げ": 6000.0,
        "う巻": 18000.0,
        "おしんこ盛": 2800.0,
        "おまかせコース": 25000.0,
        "お通し": 25900.0,
        "ぎんだら焼": 3600.0,
        "さつま揚げ": 900.0,
        "しき焼酎(芋)": 800.0,
        "しき焼酎(麦)": 7500.0,
        "しょうが焼き定食": 1200.0,
        "たこの唐揚げ": 2000.0,
        "ふぐ刺し": 15000.0,
        "ほうれん草胡麻和え": 2400.0,
        "ゆず酒": 800.0,
        "ウーロン茶": 5400.0,
        "エシャレット": 2400.0,
        "オレンジジュース": 600.0,
        "オールフリー": 600.0,
        "カキフライ1個": 2000.0,
        "ガツ刺し": 3000.0,
        "グレンフィディックボトル": 14000.0,
        "コーラ": 1100.0,
        "サバの一夜干し": 2400.0,
        "ジンジャーエール": 800.0,
        "ズワイガニと春菊": 2200.0,
        "トマトじゃこ": 2700.0,
        "ハートランド": 900.0,
        "フードフリー": 17600.0,
        "フードフリー税込": 1300.0,
        "ボトルセット)水": 300.0,
        "ボトルセット)氷": 3600.0,
        "ボトルセット)炭酸": 10800.0,
        "マグロ山かけ": 1100.0,
        "マグロ納豆": 2000.0,
        "メヒカリのから揚げ": 1200.0,
        "ライス": 600.0,
        "ランチうな重": 44000.0,
        "ランチうな重ハーフ": 14000.0,
        "ランチコース": 105000.0,
        "ランチビール": 2400.0,
        "ランチ松セット1ドリンク": 51040.0,
        "ロケットナウうな重松": 27600.0,
        "ロケットナウうな重梅": 8400.0,
        "ロケットナウうな重竹": 34800.0,
        "ロケットナウおしんこ盛り": 1540.0,
        "ロケットナウほうれん草胡麻和え": 1760.0,
        "ロケットナウタコ唐": 1100.0,
        "ロケットナウ山椒小袋": 270.0,
        "ロケットナウ肝焼き": 1200.0,
        "ロケットナウ骨せんべい": 800.0,
        "ロケットナウ鰻のタレ": 2400.0,
        "三岳 グラス": 6800.0,
        "三岳 ボトル": 6500.0,
        "亀泉": 1300.0,
        "内臓美人茶": 2100.0,
        "冷やしトマト": 3200.0,
        "吉四六 グラス": 2550.0,
        "吉四六 ボトル": 6500.0,
        "味噌汁": 600.0,
        "大和芋のとろろサラダ": 1400.0,
        "大和芋のサラダ ﾊｰﾌ": 2000.0,
        "大和芋の磯辺揚": 5000.0,
        "大盛り": 3400.0,
        "太刀魚の春巻き": 2000.0,
        "旬菜3点盛り": 9900.0,
        "梅干し": 600.0,
        "梅酒": 800.0,
        "牡蠣フライ2個": 4500.0,
        "特選抹茶割": 1000.0,
        "生レモンサワー": 2400.0,
        "生ｸﾞﾚｰﾌﾟﾌﾙｰﾂｻﾜｰ": 900.0,
        "白州": 1800.0,
        "緑茶": 900.0,
        "縞ホッケ焼": 1300.0,
        "肝わさ": 1200.0,
        "肝吸": 300.0,
        "肝吸い": 300.0,
        "肝吸い変更": 600.0,
        "肝焼き": 4200.0,
        "自家製らっきょう": 1400.0,
        "蟹味噌クリームコロッケ": 2000.0,
        "西の関": 2000.0,
        "豆腐サラダ": 1000.0,
        "豆腐サラダ ハーフ": 1800.0,
        "酔鯨": 1100.0,
        "銀盤純米大吟醸": 3600.0,
        "馬刺 赤身": 7000.0,
        "馬刺し盛り合わせ": 7200.0,
        "骨せんべい": 1200.0,
        "鰻ぷりん": 1200.0,
        "麻布しきコース": 50000.0,
        "麻布しき本店満喫コース": 28000.0,
        "ｱｻﾋｽｰﾊﾟｰﾄﾞﾗｲ(瓶)": 900.0,
        "ｸﾞﾚﾝﾌﾃﾞｨｯｸ12年": 2700.0,
        "ｻﾞ･ﾌﾟﾚﾐｱﾑ･ﾓﾙﾂ 小生": 900.0,
        "ｻﾞ･ﾌﾟﾚﾐｱﾑ･ﾓﾙﾂ ﾀﾝﾌﾞﾗｰ": 21700.0,
        "ﾒｰｶｰｽﾞﾏｰｸ": 1800.0
      },
      "quantity": {
        "TOうなぎ白焼き": 1,
        "TOうなぎ蒲焼": 1,
        "TOうな重松": 4,
        "TOうな重梅": 1,
        "TOうな重竹": 3,
        "TOう巻": 1,
        "TOフリー": 1,
        "Uberうな重ハーフ肝焼き入り": 6,
        "Uberうな重松": 18,
        "Uberうな重梅": 28,
        "Uberうな重梅 肝吸いなし": 2,
        "Uberうな重竹": 20,
        "Uberうな重竹 肝吸いなし": 1,
        "Uberう巻": 2,
        "Uberおしんこ盛り": 2,
        "Uberかきフライ": 2,
        "Uberぎんだら焼": 1,
        "Uberとろろサラダ": 8,
        "Uberほうれん草胡麻和え": 2,
        "Uberガツ刺し": 1,
        "Uberタコ唐": 2,
        "Uberヒレ唐揚げ": 1,
        "Uber大和芋いそべ揚げ": 1,
        "Uber山椒小袋": 17,
        "Uber白焼き": 5,
        "Uber肝焼き": 18,
        "Uber豆腐サラダ": 2,
        "Uber鰻のタレ": 9,
        "Uber鶏唐揚げ": 4,
        "あじ": 1,
        "うなぎヒレ唐揚げ": 2,
        "うなぎ白焼き": 3,
        "うなぎ白焼き(ハーフ)": 3,
        "うなぎ蒲焼": 1,
        "うなとろ丼": 3,
        "うな玉丼": 4,
        "うな重松": 6,
        "うな重梅": 15,
        "うな重竹": 5,
        "うまから揚げ": 6,
        "う巻": 4,
        "おしんこ盛": 4,
        "おまかせコース": 3,
        "お通し": 37,
        "ぎんだら焼": 2,
        "さつま揚げ": 1,
        "しき焼酎(芋)": 1,
        "しき焼酎(麦)": 9,
        "しょうが焼き定食": 1,
        "たこの唐揚げ": 2,
        "ふぐ刺し": 3,
        "ほうれん草胡麻和え": 3,
        "ゆず酒": 1,
        "ウーロン茶": 14,
        "エシャレット": 3,
        "オレンジジュース": 2,
        "オールフリー": 1,
        "カキフライ1個": 4,
        "ガツ刺し": 3,
        "グレンフィディックボトル": 1,
        "コーラ": 3,
        "サバの一夜干し": 2,
        "ジンジャーエール": 2,
        "ズワイガニと春菊": 2,
        "トマトじゃこ": 3,
        "ハートランド": 1,
        "フードフリー": 11,
        "フードフリー税込": 1,
        "ボトルセット)水": 1,
        "ボトルセット)氷": 12,
        "ボトルセット)炭酸": 18,
        "マグロ山かけ": 1,
        "マグロ納豆": 2,
        "メヒカリのから揚げ": 1,
        "ライス": 3,
        "ランチうな重": 8,
        "ランチうな重ハーフ": 4,
        "ランチコース": 15,
        "ランチビール": 4,
        "ランチ松セット1ドリンク": 9,
        "ロケットナウうな重松": 4,
        "ロケットナウうな重梅": 2,
        "ロケットナウうな重竹": 6,
        "ロケットナウおしんこ盛り": 2,
        "ロケットナウほうれん草胡麻和え": 2,
        "ロケットナウタコ唐": 1,
        "ロケットナウ山椒小袋": 9,
        "ロケットナウ肝焼き": 2,
        "ロケットナウ骨せんべい": 1,
        "ロケットナウ鰻のタレ": 8,
        "三岳 グラス": 8,
        "三岳 ボトル": 1,
        "亀泉": 1,
        "内臓美人茶": 3,
        "冷やしトマト": 4,
        "吉四六 グラス": 3,
        "吉四六 ボトル": 1,
        "味噌汁": 2,
        "大和芋のとろろサラダ": 1,
        "大和芋のサラダ ﾊｰﾌ": 2,
        "大和芋の磯辺揚": 5,
        "大盛り": 17,
        "太刀魚の春巻き": 2,
        "旬菜3点盛り": 10,
        "梅干し": 3,
        "梅酒": 1,
        "牡蠣フライ2個": 4,
        "特選抹茶割": 1,
        "生レモンサワー": 3,
        "生ｸﾞﾚｰﾌﾟﾌﾙｰﾂｻﾜｰ": 1,
        "白州": 1,
        "緑茶": 3,
        "縞ホッケ焼": 1,
        "肝わさ": 1,
        "肝吸": 1,
        "肝吸い": 1,
        "肝吸い変更": 2,
        "肝焼き": 7,
        "自家製らっきょう": 2,
        "蟹味噌クリームコロッケ": 2,
        "西の関": 2,
        "豆腐サラダ": 1,
        "豆腐サラダ ハーフ": 2,
        "酔鯨": 1,
        "銀盤純米大吟醸": 3,
        "馬刺 赤身": 5,
        "馬刺し盛り合わせ": 2,
        "骨せんべい": 2,
        "鰻ぷりん": 2,
        "麻布しきコース": 5,
        "麻布しき本店満喫コース": 2,
        "ｱｻﾋｽｰﾊﾟｰﾄﾞﾗｲ(瓶)": 1,
        "ｸﾞﾚﾝﾌﾃﾞｨｯｸ12年": 3,
        "ｻﾞ･ﾌﾟﾚﾐｱﾑ･ﾓﾙﾂ 小生": 2,
        "ｻﾞ･ﾌﾟﾚﾐｱﾑ･ﾓﾙﾂ ﾀﾝﾌﾞﾗｰ": 31,
        "ﾒｰｶｰｽﾞﾏｰｸ": 2
      },
      "構成比": {
        "TOうなぎ白焼き": 0.372501909072284,
        "TOうなぎ蒲焼": 0.372501909072284,
        "TOうな重松": 1.7135087817325065,
        "TOうな重梅": 0.2607513363505988,
        "TOうな重竹": 1.0802555363096236,
        "TOう巻": 0.27937643180421295,
        "TOフリー": 0.0186250954536142,
        "Uberうな重ハーフ肝焼き入り": 2.346762027155389,
        "Uberうな重松": 10.504553835838408,
        "Uberうな重梅": 9.908550781322754,
        "Uberうな重梅 肝吸いなし": 0.6705034363301112,
        "Uberうな重竹": 9.685049635879384,
        "Uberうな重竹 肝吸いなし": 0.465627386340355,
        "Uberう巻": 0.7574205484469775,
        "Uberおしんこ盛り": 0.1117505727216852,
        "Uberかきフライ": 0.23591787574577988,
        "Uberぎんだら焼": 0.18004258938493725,
        "Uberとろろサラダ": 1.043005345402395,
        "Uberほうれん草胡麻和え": 0.1490007636289136,
        "Uberガツ刺し": 0.11795893787288994,
        "Uberタコ唐": 0.2235011454433704,
        "Uberヒレ唐揚げ": 0.0558752863608426,
        "Uber大和芋いそべ揚げ": 0.11795893787288994,
        "Uber山椒小袋": 0.03166266227114414,
        "Uber白焼き": 2.6695970150180353,
        "Uber肝焼き": 0.8381292954126389,
        "Uber豆腐サラダ": 0.23591787574577988,
        "Uber鰻のタレ": 0.1676258590825278,
        "Uber鶏唐揚げ": 0.4470022908867408,
        "あじ": 0.0745003818144568,
        "うなぎヒレ唐揚げ": 0.08691711211686626,
        "うなぎ白焼き": 1.1175057272168518,
        "うなぎ白焼き(ハーフ)": 0.6705034363301112,
        "うなぎ蒲焼": 0.372501909072284,
        "うなとろ丼": 0.5364027490640889,
        "うな玉丼": 0.6903702048139664,
        "うな重松": 2.5702631725987595,
        "うな重梅": 3.911270045258982,
        "うな重竹": 1.8004258938493727,
        "うまから揚げ": 0.372501909072284,
        "う巻": 1.1175057272168518,
        "おしんこ盛": 0.17383422423373251,
        "おまかせコース": 1.5520912878011832,
        "お通し": 1.6079665741620257,
        "ぎんだら焼": 0.2235011454433704,
        "さつま揚げ": 0.0558752863608426,
        "しき焼酎(芋)": 0.04966692120963787,
        "しき焼酎(麦)": 0.465627386340355,
        "しょうが焼き定食": 0.0745003818144568,
        "たこの唐揚げ": 0.12416730302409466,
        "ふぐ刺し": 0.93125477268071,
        "ほうれん草胡麻和え": 0.1490007636289136,
        "ゆず酒": 0.04966692120963787,
        "ウーロン茶": 0.3352517181650556,
        "エシャレット": 0.1490007636289136,
        "オレンジジュース": 0.0372501909072284,
        "オールフリー": 0.0372501909072284,
        "カキフライ1個": 0.12416730302409466,
        "ガツ刺し": 0.186250954536142,
        "グレンフィディックボトル": 0.8691711211686626,
        "コーラ": 0.06829201666325206,
        "サバの一夜干し": 0.1490007636289136,
        "ジンジャーエール": 0.04966692120963787,
        "ズワイガニと春菊": 0.13658403332650412,
        "トマトじゃこ": 0.1676258590825278,
        "ハートランド": 0.0558752863608426,
        "フードフリー": 1.092672266612033,
        "フードフリー税込": 0.08070874696566153,
        "ボトルセット)水": 0.0186250954536142,
        "ボトルセット)氷": 0.2235011454433704,
        "ボトルセット)炭酸": 0.6705034363301112,
        "マグロ山かけ": 0.06829201666325206,
        "マグロ納豆": 0.12416730302409466,
        "メヒカリのから揚げ": 0.0745003818144568,
        "ライス": 0.0372501909072284,
        "ランチうな重": 2.7316806665300826,
        "ランチうな重ハーフ": 0.8691711211686626,
        "ランチコース": 6.518783408764969,
        "ランチビール": 0.1490007636289136,
        "ランチ松セット1ドリンク": 3.1687495731748956,
        "ロケットナウうな重松": 1.7135087817325065,
        "ロケットナウうな重梅": 0.5215026727011975,
        "ロケットナウうな重竹": 2.160511072619247,
        "ロケットナウおしんこ盛り": 0.09560882332855289,
        "ロケットナウほうれん草胡麻和え": 0.10926722666120331,
        "ロケットナウタコ唐": 0.06829201666325206,
        "ロケットナウ山椒小袋": 0.01676258590825278,
        "ロケットナウ肝焼き": 0.0745003818144568,
        "ロケットナウ骨せんべい": 0.04966692120963787,
        "ロケットナウ鰻のタレ": 0.1490007636289136,
        "三岳 グラス": 0.42216883028192187,
        "三岳 ボトル": 0.40354373482830763,
        "亀泉": 0.08070874696566153,
        "内臓美人茶": 0.1303756681752994,
        "冷やしトマト": 0.1986676848385515,
        "吉四六 グラス": 0.15831331135572072,
        "吉四六 ボトル": 0.40354373482830763,
        "味噌汁": 0.0372501909072284,
        "大和芋のとろろサラダ": 0.08691711211686626,
        "大和芋のサラダ ﾊｰﾌ": 0.12416730302409466,
        "大和芋の磯辺揚": 0.31041825756023667,
        "大盛り": 0.21108441514096093,
        "太刀魚の春巻き": 0.12416730302409466,
        "旬菜3点盛り": 0.6146281499692685,
        "梅干し": 0.0372501909072284,
        "梅酒": 0.04966692120963787,
        "牡蠣フライ2個": 0.27937643180421295,
        "特選抹茶割": 0.06208365151204733,
        "生レモンサワー": 0.1490007636289136,
        "生ｸﾞﾚｰﾌﾟﾌﾙｰﾂｻﾜｰ": 0.0558752863608426,
        "白州": 0.1117505727216852,
        "緑茶": 0.0558752863608426,
        "縞ホッケ焼": 0.08070874696566153,
        "肝わさ": 0.0745003818144568,
        "肝吸": 0.0186250954536142,
        "肝吸い": 0.0186250954536142,
        "肝吸い変更": 0.0372501909072284,
        "肝焼き": 0.2607513363505988,
        "自家製らっきょう": 0.08691711211686626,
        "蟹味噌クリームコロッケ": 0.12416730302409466,
        "西の関": 0.12416730302409466,
        "豆腐サラダ": 0.06208365151204733,
        "豆腐サラダ ハーフ": 0.1117505727216852,
        "酔鯨": 0.06829201666325206,
        "銀盤純米大吟醸": 0.2235011454433704,
        "馬刺 赤身": 0.4345855605843313,
        "馬刺し盛り合わせ": 0.4470022908867408,
        "骨せんべい": 0.0745003818144568,
        "鰻ぷりん": 0.0745003818144568,
        "麻布しきコース": 3.1041825756023664,
        "麻布しき本店満喫コース": 1.7383422423373251,
        "ｱｻﾋｽｰﾊﾟｰﾄﾞﾗｲ(瓶)": 0.0558752863608426,
        "ｸﾞﾚﾝﾌﾃﾞｨｯｸ12年": 0.1676258590825278,
        "ｻﾞ･ﾌﾟﾚﾐｱﾑ･ﾓﾙﾂ 小生": 0.0558752863608426,
        "ｻﾞ･ﾌﾟﾚﾐｱﾑ･ﾓﾙﾂ ﾀﾝﾌﾞﾗｰ": 1.3472152378114273,
        "ﾒｰｶｰｽﾞﾏｰｸ": 0.1117505727216852
      }
    }
  },
  "reviews_analysis": {
    "target_week_count": 0,
    "target_week_reviews": []
  }
}